layered_settings/__init__.py
layered_settings/layered_settings.py
layered_settings/loaders/__init__.py
layered_settings/loaders/base_loader.py
layered_settings/loaders/callable_loader.py
layered_settings/loaders/config_parser_loader.py
layered_settings/loaders/dict_loader.py
layered_settings/loaders/env_loader.py
layered_settings/loaders/secrets_manager_loader.py
layered_settings/loaders/ssm_loader.py
tests/__init__.py
tests/tests.py
layered_settings-1.1.0.dist-info/LICENSE
layered_settings-1.1.0.dist-info/METADATA
layered_settings-1.1.0.dist-info/WHEEL
layered_settings-1.1.0.dist-info/top_level.txt
layered_settings-1.1.0.dist-info/RECORD
