Metadata-Version: 2.1
Name: layered-settings
Version: 1.1.0
Summary: Flexible, simple, extensible settings loader from environment, AWS SSM, AWS Secrets Manager, configparser .ini, and more.
Home-page: https://github.com/mathandpencil/layered-settings
Author: Scott Stafford
Author-email: scott.stafford+layered@gmail.com
Classifier: Programming Language :: Python :: 3
Classifier: License :: OSI Approved :: MIT License
Classifier: Operating System :: OS Independent
License-File: LICENSE
Provides-Extra: aws
Requires-Dist: boto3 ; extra == 'aws'
Provides-Extra: ssm
Requires-Dist: boto3 ; extra == 'ssm'
